cogbooks/__init__.py
cogbooks/_functions.py
cogbooks/_version.py
cogbooks-0.10.0.dist-info/LICENSE.txt
cogbooks-0.10.0.dist-info/METADATA
cogbooks-0.10.0.dist-info/WHEEL
cogbooks-0.10.0.dist-info/entry_points.txt
cogbooks-0.10.0.dist-info/top_level.txt
cogbooks-0.10.0.dist-info/RECORD
