Metadata-Version: 2.1
Name: cogbooks
Version: 0.10.0
Summary: Convert instructor jupytext-markdown to student notebooks, removing all solutions
Home-page: https://github.com/CogWorksBWSI/Cogbooks
Author: Petar Griggs
Author-email: marrs2k@gmail.com
License: UNKNOWN
Platform: UNKNOWN
Requires-Python: >=3.6
License-File: LICENSE.txt
Requires-Dist: jupytext (>=1.2.0)
